DouAPI-1.0.0.dist-info/DESCRIPTION.rst
DouAPI-1.0.0.dist-info/METADATA
DouAPI-1.0.0.dist-info/RECORD
DouAPI-1.0.0.dist-info/WHEEL
DouAPI-1.0.0.dist-info/metadata.json
DouAPI-1.0.0.dist-info/top_level.txt
dou/__init__.py
dou/api.py
