Metadata-Version: 2.0
Name: DouAPI
Version: 1.0.0
Summary: Dou API wrapper
Home-page: https://github.com/DmytryiStriletskyi/DouAPI
Author: DmytryiStriletskyi
Author-email: dmytryi.striletskyi@gmail.com
License: MIT
Download-URL: https://github.com/DmytryiStriletskyi/DouAPI/archive/master.zip
Platform: UNKNOWN
Classifier: License :: OSI Approved :: MIT License
Classifier: Programming Language :: Python :: 3.5
Requires-Dist: requests
